<?xml version="1.0" encoding="UTF-8" standalone="no"?><bugrepository name="ARIES">
  
  <bug fixdate="2018-11-31 01:00:00" id="1806" opendate="2018-5-31 00:00:00" resolution="Fixed">
    <buginformation>
      <summary>Support to create prototype scoped services</summary>
      <description>It would be nice if one could specify that the type of service produced for the SPI type is prototype scoped.</description>
      <version>None</version>
      <fixedVersion>spifly-1.2</fixedVersion>
      <type>New Feature</type>
    </buginformation>
    <fixedFiles>
      <file type="M">spi-fly.spi-fly-core.src.main.java.org.apache.aries.spifly.ProviderBundleTrackerCustomizer.java</file>
    </fixedFiles>
  </bug>
</bugrepository>